{
  "fill" : "automatic",
  "groups" : [
    {
      "layers" : [
        {
          "image-name" : "Photos Server Icon 4 vivid clipped 2.png",
          "name" : "Photos Server Icon 4 vivid clipped 2",
          "position" : {
            "scale" : 1.15,
            "translation-in-points" : [
              0,
              0
            ]
          }
        }
      ],
      "shadow" : {
        "kind" : "neutral",
        "opacity" : 0.5
      },
      "translucency" : {
        "enabled" : true,
        "value" : 0.5
      }
    }
  ],
  "supported-platforms" : {
    "circles" : [
      "watchOS"
    ],
    "squares" : "shared"
  }
}